Metadata-Version: 2.1
Name: nulink-twisted
Version: 0.1.0
Summary: An asynchronous networking framework written in Python
Home-page: https://twistedmatrix.com/
Author: Twisted Matrix Laboratories
Author-email: twisted-python@twistedmatrix.com
Maintainer: Glyph Lefkowitz
Maintainer-email: glyph@twistedmatrix.com
License: MIT
Project-URL: Documentation, https://docs.twistedmatrix.com/
Project-URL: Source, https://github.com/twisted/twisted
Project-URL: Issues, https://twistedmatrix.com/trac/report
Project-URL: Twitter, https://twitter.com/twistedmatrix
Project-URL: Changelog, https://github.com/twisted/twisted/blob/HEAD/NEWS.rst
Platform: UNKNOWN
Classifier: Programming Language :: Python :: 3
Classifier: Programming Language :: Python :: 3 :: Only
Classifier: Programming Language :: Python :: 3.6
Classifier: Programming Language :: Python :: 3.7
Classifier: Programming Language :: Python :: 3.8
Classifier: Programming Language :: Python :: 3.9
Classifier: Programming Language :: Python :: 3.10
Requires-Python: >=3.6.7
License-File: LICENSE
Requires-Dist: zope.interface (>=4.4.2)
Requires-Dist: constantly (>=15.1)
Requires-Dist: incremental (>=21.3.0)
Requires-Dist: Automat (>=0.8.0)
Requires-Dist: hyperlink (>=17.1.1)
Requires-Dist: attrs (>=19.2.0)
Requires-Dist: typing-extensions (>=3.6.5)
Requires-Dist: twisted-iocpsupport (<2,>=1.0.2) ; platform_system == "Windows"
Provides-Extra: all_non_platform
Requires-Dist: cython-test-exception-raiser (<2,>=1.0.2) ; extra == 'all_non_platform'
Requires-Dist: PyHamcrest (>=1.9.0) ; extra == 'all_non_platform'
Requires-Dist: pyopenssl (>=16.0.0) ; extra == 'all_non_platform'
Requires-Dist: service-identity (>=18.1.0) ; extra == 'all_non_platform'
Requires-Dist: idna (>=2.4) ; extra == 'all_non_platform'
Requires-Dist: pyasn1 ; extra == 'all_non_platform'
Requires-Dist: cryptography (>=2.6) ; extra == 'all_non_platform'
Requires-Dist: appdirs (>=1.4.0) ; extra == 'all_non_platform'
Requires-Dist: bcrypt (>=3.0.0) ; extra == 'all_non_platform'
Requires-Dist: pyserial (>=3.0) ; extra == 'all_non_platform'
Requires-Dist: h2 (<5.0,>=3.0) ; extra == 'all_non_platform'
Requires-Dist: priority (<2.0,>=1.1.0) ; extra == 'all_non_platform'
Requires-Dist: pywin32 (!=226) ; (platform_system == "Windows") and extra == 'all_non_platform'
Requires-Dist: contextvars (<3,>=2.4) ; (python_version < "3.7") and extra == 'all_non_platform'
Provides-Extra: conch
Requires-Dist: pyasn1 ; extra == 'conch'
Requires-Dist: cryptography (>=2.6) ; extra == 'conch'
Requires-Dist: appdirs (>=1.4.0) ; extra == 'conch'
Requires-Dist: bcrypt (>=3.0.0) ; extra == 'conch'
Provides-Extra: conch_nacl
Requires-Dist: pyasn1 ; extra == 'conch_nacl'
Requires-Dist: cryptography (>=2.6) ; extra == 'conch_nacl'
Requires-Dist: appdirs (>=1.4.0) ; extra == 'conch_nacl'
Requires-Dist: bcrypt (>=3.0.0) ; extra == 'conch_nacl'
Requires-Dist: PyNaCl ; extra == 'conch_nacl'
Provides-Extra: contextvars
Requires-Dist: contextvars (<3,>=2.4) ; (python_version < "3.7") and extra == 'contextvars'
Provides-Extra: dev
Requires-Dist: towncrier (~=19.2) ; extra == 'dev'
Requires-Dist: sphinx-rtd-theme (~=0.5) ; extra == 'dev'
Requires-Dist: readthedocs-sphinx-ext (~=2.1) ; extra == 'dev'
Requires-Dist: sphinx (<6,>=4.1.2) ; extra == 'dev'
Requires-Dist: pyflakes (~=2.2) ; extra == 'dev'
Requires-Dist: twistedchecker (~=0.7) ; extra == 'dev'
Requires-Dist: coverage (<7,>=6b1) ; extra == 'dev'
Requires-Dist: python-subunit (~=1.4) ; (python_version < "3.10") and extra == 'dev'
Requires-Dist: pydoctor (~=21.9.0) ; (python_version >= "3.6") and extra == 'dev'
Provides-Extra: dev_release
Requires-Dist: towncrier (~=19.2) ; extra == 'dev_release'
Requires-Dist: sphinx-rtd-theme (~=0.5) ; extra == 'dev_release'
Requires-Dist: readthedocs-sphinx-ext (~=2.1) ; extra == 'dev_release'
Requires-Dist: sphinx (<6,>=4.1.2) ; extra == 'dev_release'
Requires-Dist: pydoctor (~=21.9.0) ; (python_version >= "3.6") and extra == 'dev_release'
Provides-Extra: http2
Requires-Dist: h2 (<5.0,>=3.0) ; extra == 'http2'
Requires-Dist: priority (<2.0,>=1.1.0) ; extra == 'http2'
Provides-Extra: macos_platform
Requires-Dist: pyobjc-core ; extra == 'macos_platform'
Requires-Dist: pyobjc-framework-CFNetwork ; extra == 'macos_platform'
Requires-Dist: pyobjc-framework-Cocoa ; extra == 'macos_platform'
Requires-Dist: cython-test-exception-raiser (<2,>=1.0.2) ; extra == 'macos_platform'
Requires-Dist: PyHamcrest (>=1.9.0) ; extra == 'macos_platform'
Requires-Dist: pyopenssl (>=16.0.0) ; extra == 'macos_platform'
Requires-Dist: service-identity (>=18.1.0) ; extra == 'macos_platform'
Requires-Dist: idna (>=2.4) ; extra == 'macos_platform'
Requires-Dist: pyasn1 ; extra == 'macos_platform'
Requires-Dist: cryptography (>=2.6) ; extra == 'macos_platform'
Requires-Dist: appdirs (>=1.4.0) ; extra == 'macos_platform'
Requires-Dist: bcrypt (>=3.0.0) ; extra == 'macos_platform'
Requires-Dist: pyserial (>=3.0) ; extra == 'macos_platform'
Requires-Dist: h2 (<5.0,>=3.0) ; extra == 'macos_platform'
Requires-Dist: priority (<2.0,>=1.1.0) ; extra == 'macos_platform'
Requires-Dist: pywin32 (!=226) ; (platform_system == "Windows") and extra == 'macos_platform'
Requires-Dist: contextvars (<3,>=2.4) ; (python_version < "3.7") and extra == 'macos_platform'
Provides-Extra: mypy
Requires-Dist: mypy (==0.930) ; extra == 'mypy'
Requires-Dist: mypy-zope (==0.3.4) ; extra == 'mypy'
Requires-Dist: types-setuptools ; extra == 'mypy'
Requires-Dist: types-pyOpenSSL ; extra == 'mypy'
Requires-Dist: towncrier (~=19.2) ; extra == 'mypy'
Requires-Dist: sphinx-rtd-theme (~=0.5) ; extra == 'mypy'
Requires-Dist: readthedocs-sphinx-ext (~=2.1) ; extra == 'mypy'
Requires-Dist: sphinx (<6,>=4.1.2) ; extra == 'mypy'
Requires-Dist: pyflakes (~=2.2) ; extra == 'mypy'
Requires-Dist: twistedchecker (~=0.7) ; extra == 'mypy'
Requires-Dist: coverage (<7,>=6b1) ; extra == 'mypy'
Requires-Dist: cython-test-exception-raiser (<2,>=1.0.2) ; extra == 'mypy'
Requires-Dist: PyHamcrest (>=1.9.0) ; extra == 'mypy'
Requires-Dist: pyopenssl (>=16.0.0) ; extra == 'mypy'
Requires-Dist: service-identity (>=18.1.0) ; extra == 'mypy'
Requires-Dist: idna (>=2.4) ; extra == 'mypy'
Requires-Dist: pyasn1 ; extra == 'mypy'
Requires-Dist: cryptography (>=2.6) ; extra == 'mypy'
Requires-Dist: appdirs (>=1.4.0) ; extra == 'mypy'
Requires-Dist: bcrypt (>=3.0.0) ; extra == 'mypy'
Requires-Dist: pyserial (>=3.0) ; extra == 'mypy'
Requires-Dist: h2 (<5.0,>=3.0) ; extra == 'mypy'
Requires-Dist: priority (<2.0,>=1.1.0) ; extra == 'mypy'
Requires-Dist: PyNaCl ; extra == 'mypy'
Requires-Dist: pywin32 (!=226) ; (platform_system == "Windows") and extra == 'mypy'
Requires-Dist: python-subunit (~=1.4) ; (python_version < "3.10") and extra == 'mypy'
Requires-Dist: contextvars (<3,>=2.4) ; (python_version < "3.7") and extra == 'mypy'
Requires-Dist: pydoctor (~=21.9.0) ; (python_version >= "3.6") and extra == 'mypy'
Provides-Extra: osx_platform
Requires-Dist: pyobjc-core ; extra == 'osx_platform'
Requires-Dist: pyobjc-framework-CFNetwork ; extra == 'osx_platform'
Requires-Dist: pyobjc-framework-Cocoa ; extra == 'osx_platform'
Requires-Dist: cython-test-exception-raiser (<2,>=1.0.2) ; extra == 'osx_platform'
Requires-Dist: PyHamcrest (>=1.9.0) ; extra == 'osx_platform'
Requires-Dist: pyopenssl (>=16.0.0) ; extra == 'osx_platform'
Requires-Dist: service-identity (>=18.1.0) ; extra == 'osx_platform'
Requires-Dist: idna (>=2.4) ; extra == 'osx_platform'
Requires-Dist: pyasn1 ; extra == 'osx_platform'
Requires-Dist: cryptography (>=2.6) ; extra == 'osx_platform'
Requires-Dist: appdirs (>=1.4.0) ; extra == 'osx_platform'
Requires-Dist: bcrypt (>=3.0.0) ; extra == 'osx_platform'
Requires-Dist: pyserial (>=3.0) ; extra == 'osx_platform'
Requires-Dist: h2 (<5.0,>=3.0) ; extra == 'osx_platform'
Requires-Dist: priority (<2.0,>=1.1.0) ; extra == 'osx_platform'
Requires-Dist: pywin32 (!=226) ; (platform_system == "Windows") and extra == 'osx_platform'
Requires-Dist: contextvars (<3,>=2.4) ; (python_version < "3.7") and extra == 'osx_platform'
Provides-Extra: serial
Requires-Dist: pyserial (>=3.0) ; extra == 'serial'
Requires-Dist: pywin32 (!=226) ; (platform_system == "Windows") and extra == 'serial'
Provides-Extra: test
Requires-Dist: cython-test-exception-raiser (<2,>=1.0.2) ; extra == 'test'
Requires-Dist: PyHamcrest (>=1.9.0) ; extra == 'test'
Provides-Extra: tls
Requires-Dist: pyopenssl (>=16.0.0) ; extra == 'tls'
Requires-Dist: service-identity (>=18.1.0) ; extra == 'tls'
Requires-Dist: idna (>=2.4) ; extra == 'tls'
Provides-Extra: windows_platform
Requires-Dist: pywin32 (!=226) ; extra == 'windows_platform'
Requires-Dist: cython-test-exception-raiser (<2,>=1.0.2) ; extra == 'windows_platform'
Requires-Dist: PyHamcrest (>=1.9.0) ; extra == 'windows_platform'
Requires-Dist: pyopenssl (>=16.0.0) ; extra == 'windows_platform'
Requires-Dist: service-identity (>=18.1.0) ; extra == 'windows_platform'
Requires-Dist: idna (>=2.4) ; extra == 'windows_platform'
Requires-Dist: pyasn1 ; extra == 'windows_platform'
Requires-Dist: cryptography (>=2.6) ; extra == 'windows_platform'
Requires-Dist: appdirs (>=1.4.0) ; extra == 'windows_platform'
Requires-Dist: bcrypt (>=3.0.0) ; extra == 'windows_platform'
Requires-Dist: pyserial (>=3.0) ; extra == 'windows_platform'
Requires-Dist: h2 (<5.0,>=3.0) ; extra == 'windows_platform'
Requires-Dist: priority (<2.0,>=1.1.0) ; extra == 'windows_platform'
Requires-Dist: pywin32 (!=226) ; (platform_system == "Windows") and extra == 'windows_platform'
Requires-Dist: contextvars (<3,>=2.4) ; (python_version < "3.7") and extra == 'windows_platform'
